{
    "configuration": {
        "arch_config": "/scratch/user/sabuj.laskar/SuperMesh_2/src/SCALE-Sim/configs/express_128.cfg",
        "num_hmcs": 16,
        "num_vaults": 1,
        "mini_batch_size": 32,
        "network": "/scratch/user/sabuj.laskar/SuperMesh_2/src/SCALE-Sim/topologies/CIFAR10_main_models/resnet50.csv",
        "run_name": "resnet50",
        "outdir": "/scratch/user/sabuj.laskar/SuperMesh_2/results/micro2025/compute_short_128_b2",
        "booksim_network": "mesh",
        "booksim_config": "/scratch/user/sabuj.laskar/SuperMesh_2/src/booksim2/runfiles/mesh/anynet_mesh_16_200.cfg",
        "allreduce": "multitree",
        "verbose": false,
        "collective": "Compute",
        "message_buffer_size": 32,
        "message_size": 4096,
        "synthetic_data_size": 0,
        "bandwidth": 100,
        "load_tree": true,
        "only_save_tree": false,
        "messages_per_chunk": 3,
        "save_link_utilization": false,
        "analytical": false,
        "per_dim_nodes": 4,
        "flits_per_packet": 17,
        "radix": 4,
        "latency": 20,
        "per_message_time": 360,
        "extension": "Compute",
        "pe_array_height": 128,
        "pe_array_width": 128,
        "ifmap_sram_size": 4194304,
        "filter_sram_size": 4194304,
        "ofmap_sram_size": 4194304,
        "ifmap_offset": 0,
        "filter_offset": 10000000,
        "ofmap_offset": 20000000,
        "ifmap_grad_offset": 40000000,
        "filter_grad_offset": 50000000,
        "ofmap_grad_offset": 30000000,
        "data_flow": "os",
        "multitree_total_message": 1433,
        "nodes": 16,
        "saved_tree_name": "/scratch/user/sabuj.laskar/SuperMesh_2/src/SavedTrees/mesh/mesh_multitree_16",
        "dump": false
    },
    "results": {
        "performance": {
            "training": 1618396,
            "training_by_layer": {
                "53": 235352,
                "52": 252006,
                "51": 289128,
                "50": 305782,
                "49": 322436,
                "48": 359558,
                "47": 376212,
                "46": 409250,
                "45": 425904,
                "44": 463031,
                "43": 471541,
                "42": 475955,
                "41": 485461,
                "40": 489875,
                "39": 494289,
                "38": 503795,
                "37": 508209,
                "36": 512623,
                "35": 522129,
                "34": 526543,
                "33": 530957,
                "32": 540463,
                "31": 544877,
                "30": 549291,
                "29": 558797,
                "28": 563211,
                "27": 575817,
                "26": 580231,
                "25": 594358,
                "24": 598709,
                "23": 601011,
                "22": 605461,
                "21": 607892,
                "20": 610194,
                "19": 614644,
                "18": 617075,
                "17": 619377,
                "16": 623827,
                "15": 626258,
                "14": 636752,
                "13": 639054,
                "12": 650677,
                "11": 655156,
                "10": 659442,
                "9": 668868,
                "8": 673347,
                "7": 677633,
                "6": 687059,
                "5": 691538,
                "4": 695824,
                "3": 700110,
                "2": 709536,
                "1": 711839,
                "0": 717527
            },
            "total": 1618397,
            "allreduce": {
                "total": 1
            }
        },
        "power": {
            "network": {
                "dynamic": NaN,
                "static": 9.36868793981943,
                "total": NaN,
                "router": {
                    "dynamic": NaN,
                    "static": 9.27930968087543,
                    "total": NaN
                },
                "link": {
                    "dynamic": NaN,
                    "static": 0.08937825894400027,
                    "total": NaN,
                    "flits": 0
                }
            }
        }
    }
}